{
  "mode": "pre",
  "tag": "alpha",
  "initialVersions": {
    "@demo/wallet": "0.0.2",
    "@demo/nodejs": "0.0.5",
    "@bnb-chain/greenfield-js-sdk": "0.2.3",
    "@bnb-chain/greenfiled-file-handle": "0.2.0",
    "@bnb-chain/greenfield-zk-crypto": "0.0.1"
  },
  "changesets": [
    "angry-lies-beam",
    "blue-bugs-whisper",
    "blue-zebras-cover",
    "brave-avocados-impress",
    "clever-deers-turn",
    "cuddly-radios-wink",
    "curly-fishes-bow",
    "curvy-bears-kneel",
    "eighty-parrots-tap",
    "eleven-numbers-cover",
    "fair-impalas-approve",
    "famous-goats-visit",
    "fast-drinks-move",
    "five-mice-whisper",
    "flat-cameras-divide",
    "flat-mugs-collect",
    "fresh-emus-serve",
    "giant-panthers-collect",
    "giant-toys-march",
    "gold-bugs-occur",
    "gold-eyes-push",
    "gold-singers-grab",
    "gorgeous-ligers-give",
    "gorgeous-penguins-invite",
    "great-readers-breathe",
    "grumpy-tables-drop",
    "happy-monkeys-exist",
    "honest-countries-hear",
    "honest-tables-lick",
    "itchy-candles-fold",
    "itchy-pants-search",
    "large-jokes-fly",
    "late-mice-count",
    "lazy-needles-shave",
    "long-suits-share",
    "many-fans-decide",
    "mean-horses-change",
    "mighty-deers-build",
    "mighty-mangos-exercise",
    "modern-ties-give",
    "nice-dodos-sip",
    "nice-geckos-think",
    "ninety-jokes-study",
    "odd-hotels-glow",
    "orange-berries-jog",
    "plenty-squids-walk",
    "poor-steaks-warn",
    "proud-dragons-repair",
    "quiet-numbers-camp",
    "rich-carrots-cheer",
    "seven-toys-fry",
    "silver-avocados-march",
    "slimy-buses-smoke",
    "soft-phones-give",
    "spicy-lizards-think",
    "strong-wombats-help",
    "stupid-spies-poke",
    "swift-pigs-travel",
    "tender-sloths-shake",
    "twelve-mangos-scream",
    "unlucky-suns-look",
    "wet-trainers-whisper",
    "yellow-plums-cheat"
  ]
}
